{
   "camper": {
      "idRutaN": "3",
      "fundamentos": 0,
      "programacion web": 0,
      "programacion formal": 0,
      "bases de datos": 0,
      "backend": 0
   },
   "02": {
      "idRutaN": "1",
      "fundamentos": 66.47,
      "programacion web": 33.0,
      "programacion formal": 0,
      "bases de datos": 0,
      "backend": 0
   },
   "01": {
      "idRutaN": "3",
      "fundamentos": 66.47,
      "programacion web": 33.0,
      "programacion formal": 0,
      "bases de datos": 51.4,
      "backend": 0
   }
}